{
  "questions": [
    {
      "question": "What does a Register Transfer Level (RTL) description primarily represent in the digital IC design flow?",
      "options": [
        "The physical placement and routing of all transistors on the chip.",
        "The specific manufacturing process steps required to produce the chip.",
        "The power consumption profile and thermal characteristics of the design.",
        "The abstract behavioral and structural description of data flow between registers and combinational logic.",
        "A gate-level netlist of standard cells."
      ],
      "correct": 3
    },
    {
      "question": "In the context of a CPU's pipeline, what is a `hazard`?",
      "options": [
        "A manufacturing defect that leads to incorrect logic operation.",
        "A situation where an instruction requires data that has not yet been produced by a prior instruction in the pipeline.",
        "A critical error that causes the CPU to halt execution.",
        "An unexpected voltage fluctuation causing circuit instability.",
        "A software bug that results in an infinite loop."
      ],
      "correct": 1
    },
    {
      "question": "What is the main function of the Arithmetic Logic Unit (ALU) within a Central Processing Unit (CPU)?",
      "options": [
        "To decode program instructions into micro-operations.",
        "To store frequently accessed data for faster retrieval.",
        "To perform mathematical operations and bitwise logical comparisons.",
        "To manage communication with external peripheral devices.",
        "To control the flow of data between memory and registers."
      ],
      "correct": 2
    },
    {
      "question": "What is the primary purpose of inserting `scan chains` into a digital IC during the Design-for-Testability (DFT) phase?",
      "options": [
        "To reduce the overall gate count and silicon area of the design.",
        "To enable sequential logic (flip-flops) to be configured into shift registers, making their states controllable and observable for manufacturing defect testing.",
        "To provide a mechanism for dynamic voltage and frequency scaling (DVFS).",
        "To enhance the chip's security against reverse engineering attempts.",
        "To implement on-chip error correction codes for data integrity."
      ],
      "correct": 1
    },
    {
      "question": "In a cache memory system, what does the term `write-back` policy primarily imply about how data is updated in main memory?",
      "options": [
        "Data is immediately written to both the cache and main memory upon a write operation.",
        "The CPU polls main memory periodically to synchronize data.",
        "Write operations are delayed until the entire program finishes execution.",
        "All write operations bypass the cache and go directly to main memory.",
        "Data is only written to main memory when the modified cache block is replaced or evicted from the cache."
      ],
      "correct": 4
    }
  ]
}